pyflink_deepbi/__init__.py
pyflink_deepbi/jdbc.py
pyflink_deepbi/util.py
pyflink_deepbi-0.1.0.dist-info/METADATA
pyflink_deepbi-0.1.0.dist-info/WHEEL
pyflink_deepbi-0.1.0.dist-info/top_level.txt
pyflink_deepbi-0.1.0.dist-info/RECORD
