Metadata-Version: 2.1
Name: pyflink-deepbi
Version: 0.1.0
Summary: "Deep.BI utilities libraries for PyFlink"
Author: "Bartosz Mikulski"
Author-email: bartosz.mikulski@deep.bi, bartosz.mikulski.praca@gmail.com
License: Apache-2.0
Requires-Python: >=3.7
Requires-Dist: apache-flink (>=1.15)
